{
  "status": "closed",
  "status_since": "2026-04-19T00:00:00Z",
  "last_checked": "2026-04-20T00:00:00Z",
  "note": "Iran announced closure on 19 April 2026 citing 'repeated breaches of trust'. Traffic has been largely blocked since 28 February. The US is running a counter-blockade on Iranian ports. Things are, to use the technical term, cooked.",
  "subverdict_override": null,
  "source_title": "Iran says it's closing Strait of Hormuz again — CNN, 18 April 2026",
  "source_url": "https://www.cnn.com/2026/04/18/world/live-news/iran-war-trump-israel"
}
